aus_council_scrapers/__init__.py
aus_council_scrapers/base.py
aus_council_scrapers/constants.py
aus_council_scrapers/database.py
aus_council_scrapers/discord_bot.py
aus_council_scrapers/logging_config.py
aus_council_scrapers/logs/YIMBY-Scraper/YIMBY-Scraper.log
aus_council_scrapers/main.py
aus_council_scrapers/scrapers/__init__.py
aus_council_scrapers/scrapers/act/__init__.py
aus_council_scrapers/scrapers/nsw/__init__.py
aus_council_scrapers/scrapers/nsw/bayside_nsw.py
aus_council_scrapers/scrapers/nsw/burwood.py
aus_council_scrapers/scrapers/nsw/camden.py
aus_council_scrapers/scrapers/nsw/campbelltown.py
aus_council_scrapers/scrapers/nsw/canada_bay.py
aus_council_scrapers/scrapers/nsw/canterbury_bankstown.py
aus_council_scrapers/scrapers/nsw/cumberland.py
aus_council_scrapers/scrapers/nsw/georges_river.py
aus_council_scrapers/scrapers/nsw/hornsby.py
aus_council_scrapers/scrapers/nsw/hunters_hill.py
aus_council_scrapers/scrapers/nsw/innerwest.py
aus_council_scrapers/scrapers/nsw/kuringgai.py
aus_council_scrapers/scrapers/nsw/lane_cove.py
aus_council_scrapers/scrapers/nsw/liverpool.py
aus_council_scrapers/scrapers/nsw/north_sydney.py
aus_council_scrapers/scrapers/nsw/northern_beaches.py
aus_council_scrapers/scrapers/nsw/parramatta.py
aus_council_scrapers/scrapers/nsw/penrith_city.py
aus_council_scrapers/scrapers/nsw/randwick.py
aus_council_scrapers/scrapers/nsw/ryde.py
aus_council_scrapers/scrapers/nsw/waverley.py
aus_council_scrapers/scrapers/nsw/willoughby.py
aus_council_scrapers/scrapers/nsw/woollahra.py
aus_council_scrapers/scrapers/qld/__init__.py
aus_council_scrapers/scrapers/vic/__init__.py
aus_council_scrapers/scrapers/vic/banyule.py
aus_council_scrapers/scrapers/vic/bayside.py
aus_council_scrapers/scrapers/vic/boroondara.py
aus_council_scrapers/scrapers/vic/darebin.py
aus_council_scrapers/scrapers/vic/glen_eira.py
aus_council_scrapers/scrapers/vic/hobsons_bay.py
aus_council_scrapers/scrapers/vic/kingston.py
aus_council_scrapers/scrapers/vic/manningham.py
aus_council_scrapers-0.1.0.dist-info/METADATA
aus_council_scrapers-0.1.0.dist-info/WHEEL
aus_council_scrapers-0.1.0.dist-info/RECORD
